[
	{
		"categories": [
			"Urban",
			"Livingroom"
		],
		"description": "A round wooden table. This weathered relic from a bygone era stands as a testament to a simpler time, a stark contrast to the harsh reality surrounding it.\nThe table's surface bears the scars a history as a dining spot.",
		"destruction": {
			"group": "destroyed_furniture_medium",
			"sprite": "wreck_wood_generic_32.png"
		},
		"edgesnapping": "None",
		"id": "table_round_wood",
		"moveable": true,
		"name": "Round wooden table",
		"sprite": "table_64.png",
		"weight": 10
	},
	{
		"categories": [
			"Urban",
			"Livingroom"
		],
		"description": "A simple wooden chair, its construction is basic yet sturdy, a testament to durability in the face of decay. \nWith a rough-hewn seat and a backrest that bears the marks of time, this chair offers a momentary respite from the unforgiving environment.",
		"destruction": {
			"group": "destroyed_furniture_medium",
			"sprite": "wreck_wood_generic_32.png"
		},
		"edgesnapping": "None",
		"id": "chair_wood",
		"moveable": true,
		"name": "Wooden chair",
		"sprite": "chair_32.png",
		"weight": 2
	},
	{
		"Function": {
			"container": {
				"itemgroup": "kitchen_cupboard"
			}
		},
		"categories": [
			"Urban",
			"Kitchen",
			"Indoor"
		],
		"description": "One of the central pieces of fruniture that make up a kitchen",
		"destruction": {
			"group": "destroyed_furniture_medium",
			"sprite": "wreck_wood_generic_32.png"
		},
		"disassembly": {
			"group": "disassembled_furniture_medium",
			"sprite": "wreck_wood_generic_32.png"
		},
		"edgesnapping": "North",
		"id": "countertop_wood",
		"moveable": false,
		"name": "Wooden countertop",
		"sprite": "countertop_100_52.png"
	},
	{
		"categories": [
			"Nature"
		],
		"description": "A common tree",
		"destruction": {
			"group": "destroyed_furniture_medium",
			"sprite": "wreck_wood_generic_32.png"
		},
		"edgesnapping": "None",
		"id": "Tree_00",
		"moveable": false,
		"name": "Tree",
		"references": {
			"core": {
				"maps": [
					"field_grass_basic_00",
					"field_grass_basic_01",
					"urbanroad_t",
					"urbanroad_corner"
				]
			}
		},
		"sprite": "Tree_100.png"
	},
	{
		"categories": [
			"Nature"
		],
		"description": "A common pine tree",
		"destruction": {
			"group": "destroyed_furniture_medium",
			"sprite": "wreck_wood_generic_32.png"
		},
		"edgesnapping": "None",
		"id": "PineTree_00",
		"moveable": false,
		"name": "Pine tree",
		"references": {
			"core": {
				"maps": [
					"field_grass_basic_01",
					"urbanroad_t",
					"urbanroad_corner"
				]
			}
		},
		"sprite": "PineTree_100.png"
	},
	{
		"categories": [
			"Nature"
		],
		"description": "A common willow tree",
		"destruction": {
			"group": "destroyed_furniture_medium",
			"sprite": "wreck_wood_generic_32.png"
		},
		"edgesnapping": "None",
		"id": "WillowTree_00",
		"moveable": false,
		"name": "Willow tree",
		"references": {
			"core": {
				"maps": [
					"field_grass_basic_01",
					"urbanroad_t",
					"urbanroad_corner"
				]
			}
		},
		"sprite": "WillowTree_100.png"
	},
	{
		"categories": [
			"Urban",
			"Livingroom"
		],
		"description": "A simple wooden bench that can seat multiple people, offering a resting spot or a place for interaction.",
		"destruction": {
			"group": "destroyed_furniture_medium",
			"sprite": "wreck_wood_generic_32.png"
		},
		"edgesnapping": "North",
		"id": "bench_wood",
		"moveable": false,
		"name": "Wooden bench",
		"sprite": "bench_wood_100_50.png"
	},
	{
		"categories": [
			"Urban",
			"Livingroom"
		],
		"description": "A small pot holding a green plant, which can be placed indoors to enhance the aesthetics",
		"destruction": {

		},
		"edgesnapping": "None",
		"id": "plant_pot_00",
		"moveable": true,
		"name": "Potted plant",
		"sprite": "pot_plant_32_32.png",
		"weight": 1
	},
	{
		"categories": [
			"Urban",
			"Indoor",
			"Bedroom"
		],
		"description": "A basic wooden bed with a mattress, which could be used to rest",
		"destruction": {
			"group": "destroyed_furniture_medium",
			"sprite": "wreck_wood_generic_32.png"
		},
		"edgesnapping": "North",
		"id": "bed_wood_single_00",
		"moveable": false,
		"name": "Wooden bed",
		"sprite": "bed_wood_100_50.png"
	},
	{
		"Function": {
			"container": {
				"itemgroup": "cabinet_general"
			}
		},
		"categories": [
			"Urban",
			"Indoor"
		],
		"description": "A storage unit with doors, useful for storing items or resources that you might collect.",
		"destruction": {
			"group": "destroyed_furniture_medium",
			"sprite": "wreck_wood_generic_32.png"
		},
		"edgesnapping": "North",
		"id": "cabinet_wood_00",
		"moveable": false,
		"name": "Wooden cabinet",
		"sprite": "cabinet_wood_100_50.png"
	},
	{
		"categories": [
			"Urban",
			"Indoor"
		],
		"description": "A tall wooden bookcase with multiple shelves",
		"destruction": {
			"group": "destroyed_furniture_medium",
			"sprite": "wreck_wood_generic_32.png"
		},
		"edgesnapping": "North",
		"id": "bookcase_wood_00",
		"moveable": false,
		"name": "Wooden bookcase",
		"sprite": "bookcase_wood_100_50.png"
	},
	{
		"categories": [
			"Urban",
			"Kitchen",
			"Indoor"
		],
		"description": "One of the central pieces of fruniture that make up a kitchen",
		"destruction": {

		},
		"edgesnapping": "North",
		"id": "refrigerator_00",
		"moveable": false,
		"name": "Refrigerator",
		"sprite": "refrigerator_50_48.png"
	},
	{
		"categories": [
			"Urban",
			"Indoor"
		],
		"description": "Centerpiece of the bathroom",
		"destruction": {

		},
		"edgesnapping": "North",
		"id": "toilet_00",
		"moveable": false,
		"name": "Toilet",
		"sprite": "toilet_48.png"
	},
	{
		"Function": {
			"door": "Closed"
		},
		"categories": [
			"Urban",
			"Indoor"
		],
		"description": "It keeps people from passing trough this area. It can be opened and closed",
		"destruction": {
			"group": "destroyed_furniture_medium",
			"sprite": "wreck_wood_generic_32.png"
		},
		"edgesnapping": "North",
		"id": "door_wood",
		"moveable": false,
		"name": "Wooden door",
		"sprite": "door_100_13.png"
	}
]